turnitin_cli/__init__.py
turnitin_cli/__main__.py
turnitin_cli/core.py
turnitin_cli/test.py
turnitin_cli-1.0.2.dist-info/METADATA
turnitin_cli-1.0.2.dist-info/WHEEL
turnitin_cli-1.0.2.dist-info/top_level.txt
turnitin_cli-1.0.2.dist-info/RECORD
