Metadata-Version: 2.1
Name: turnitin-cli
Version: 1.0.2
Summary: UNKNOWN
Home-page: https://github.com/r2dev2bb8/Turnitin-CLI
Author: Ronak Badhe
Author-email: ronak.badhe@gmail.com
License: UNKNOWN
Platform: UNKNOWN
Classifier: Programming Language :: Python :: 3
Classifier: License :: OSI Approved :: MIT License
Classifier: Operating System :: OS Independent
Requires-Python: >=3.5
Requires-Dist: windows-curses (==2.1.0) ; sys_platform == "win32"
